[{"i": 7446, "s": 5}, {"i": 2566, "s": 7}, {"i": 7634, "s": 5}, {"i": 2701, "s": 14}, {"i": 7228, "s": 10}, {"i": 7414, "s": 4}, {"i": 1059, "s": 4}, {"i": 8026, "s": 5}, {"i": 3324, "s": 6}, {"i": 9324, "s": 9}, {"i": 2397, "s": 14}, {"i": 1569, "s": 9}, {"i": 6963, "s": 6}, {"i": 3136, "s": 6}, {"i": 6885, "s": 4}, {"i": 5431, "s": 16}, {"i": 5141, "s": 6}, {"i": 10479, "s": 20}, {"i": 2503, "s": 6}, {"i": 8265, "s": 7}, {"i": 9139, "s": 8}, {"i": 8637, "s": 10}, {"i": 5717, "s": 6}, {"i": 1492, "s": 8}, {"i": 2332, "s": 5}, {"i": 7025, "s": 7}, {"i": 793, "s": 9}, {"i": 7722, "s": 9}, {"i": 10677, "s": 5}, {"i": 2744, "s": 4}, {"i": 20, "s": 7}, {"i": 10268, "s": 8}, {"i": 8809, "s": 16}, {"i": 5636, "s": 12}, {"i": 10035, "s": 20}, {"i": 1154, "s": 17}, {"i": 6921, "s": 10}, {"i": 3792, "s": 4}, {"i": 7212, "s": 10}, {"i": 1067, "s": 14}, {"i": 1033, "s": 6}, {"i": 4541, "s": 4}, {"i": 7923, "s": 4}, {"i": 3296, "s": 9}, {"i": 4465, "s": 7}, {"i": 1000, "s": 6}, {"i": 920, "s": 6}, {"i": 5197, "s": 5}, {"i": 10114, "s": 19}, {"i": 3814, "s": 6}, {"i": 289, "s": 4}, {"i": 10605, "s": 5}, {"i": 7972, "s": 5}, {"i": 2896, "s": 8}, {"i": 6187, "s": 5}, {"i": 1116, "s": 7}, {"i": 1963, "s": 24}, {"i": 1946, "s": 4}, {"i": 9311, "s": 8}, {"i": 10488, "s": 7}, {"i": 125, "s": 8}, {"i": 9695, "s": 8}, {"i": 6275, "s": 11}, {"i": 6189, "s": 5}, {"i": 6532, "s": 4}, {"i": 792, "s": 4}, {"i": 190, "s": 11}, {"i": 3471, "s": 6}, {"i": 3366, "s": 8}, {"i": 1177, "s": 6}, {"i": 1956, "s": 6}, {"i": 6986, "s": 6}, {"i": 6548, "s": 9}, {"i": 3018, "s": 5}, {"i": 1051, "s": 10}, {"i": 8281, "s": 4}, {"i": 7110, "s": 23}, {"i": 7624, "s": 22}, {"i": 2955, "s": 13}, {"i": 4726, "s": 4}, {"i": 4122, "s": 21}, {"i": 5604, "s": 6}, {"i": 3434, "s": 10}, {"i": 9839, "s": 18}, {"i": 7096, "s": 16}, {"i": 7017, "s": 11}, {"i": 72, "s": 5}, {"i": 4311, "s": 5}, {"i": 3302, "s": 7}, {"i": 9523, "s": 6}, {"i": 9671, "s": 6}, {"i": 9158, "s": 6}, {"i": 8556, "s": 15}, {"i": 6861, "s": 5}, {"i": 10368, "s": 9}, {"i": 5824, "s": 4}, {"i": 2474, "s": 6}, {"i": 347, "s": 4}, {"i": 7781, "s": 12}, {"i": 7146, "s": 4}]