[{"i": 4708, "s": 13}, {"i": 4593, "s": 11}, {"i": 3893, "s": 9}, {"i": 9648, "s": 4}, {"i": 2215, "s": 7}, {"i": 7198, "s": 5}, {"i": 4445, "s": 5}, {"i": 7587, "s": 5}, {"i": 2501, "s": 7}, {"i": 8324, "s": 10}, {"i": 3211, "s": 7}, {"i": 964, "s": 7}, {"i": 6753, "s": 4}, {"i": 4406, "s": 4}, {"i": 4390, "s": 4}, {"i": 4050, "s": 7}, {"i": 8996, "s": 23}, {"i": 9632, "s": 4}, {"i": 1308, "s": 6}, {"i": 8554, "s": 11}, {"i": 5201, "s": 6}, {"i": 5833, "s": 5}, {"i": 9957, "s": 5}, {"i": 10469, "s": 13}, {"i": 1600, "s": 6}, {"i": 6328, "s": 23}, {"i": 9329, "s": 15}, {"i": 1243, "s": 9}, {"i": 2788, "s": 4}, {"i": 10103, "s": 12}, {"i": 3199, "s": 8}, {"i": 3237, "s": 4}, {"i": 3531, "s": 5}, {"i": 9803, "s": 10}, {"i": 4700, "s": 4}, {"i": 1101, "s": 6}, {"i": 4036, "s": 7}, {"i": 5371, "s": 5}, {"i": 9091, "s": 10}, {"i": 155, "s": 15}, {"i": 6496, "s": 4}, {"i": 2382, "s": 7}, {"i": 4820, "s": 7}, {"i": 3442, "s": 9}, {"i": 1297, "s": 10}, {"i": 6810, "s": 22}, {"i": 5669, "s": 4}, {"i": 8041, "s": 6}, {"i": 3122, "s": 4}, {"i": 1984, "s": 5}, {"i": 1734, "s": 9}, {"i": 5758, "s": 10}, {"i": 1706, "s": 4}, {"i": 2096, "s": 5}, {"i": 6219, "s": 10}, {"i": 5058, "s": 9}, {"i": 7932, "s": 6}, {"i": 3113, "s": 5}, {"i": 7662, "s": 5}, {"i": 3800, "s": 5}, {"i": 7194, "s": 6}, {"i": 474, "s": 4}, {"i": 8800, "s": 5}, {"i": 8635, "s": 7}, {"i": 8614, "s": 6}, {"i": 2725, "s": 9}, {"i": 1974, "s": 4}, {"i": 3879, "s": 7}, {"i": 6867, "s": 6}, {"i": 2245, "s": 5}, {"i": 3500, "s": 5}, {"i": 1631, "s": 9}, {"i": 3744, "s": 5}, {"i": 1503, "s": 5}, {"i": 1218, "s": 7}, {"i": 5142, "s": 15}, {"i": 4344, "s": 9}, {"i": 5642, "s": 5}, {"i": 6498, "s": 9}, {"i": 6657, "s": 13}, {"i": 4295, "s": 4}, {"i": 8879, "s": 9}, {"i": 8634, "s": 15}, {"i": 4537, "s": 4}, {"i": 2415, "s": 8}, {"i": 2295, "s": 4}, {"i": 3693, "s": 5}, {"i": 8062, "s": 6}, {"i": 8781, "s": 5}, {"i": 8472, "s": 7}, {"i": 1259, "s": 4}, {"i": 3388, "s": 4}, {"i": 10157, "s": 8}, {"i": 3224, "s": 14}, {"i": 7216, "s": 4}, {"i": 2884, "s": 5}, {"i": 1367, "s": 13}, {"i": 2269, "s": 6}, {"i": 2852, "s": 6}, {"i": 6563, "s": 6}]