[{"i": 2261, "s": 4}, {"i": 3244, "s": 10}, {"i": 10061, "s": 4}, {"i": 8275, "s": 3}, {"i": 9825, "s": 18}, {"i": 6760, "s": 4}, {"i": 8510, "s": 4}, {"i": 7767, "s": 6}, {"i": 5883, "s": 3}, {"i": 3076, "s": 9}, {"i": 4984, "s": 9}, {"i": 8302, "s": 4}, {"i": 5291, "s": 16}, {"i": 7599, "s": 4}, {"i": 2792, "s": 12}, {"i": 5516, "s": 3}, {"i": 7337, "s": 6}, {"i": 748, "s": 3}, {"i": 3040, "s": 10}, {"i": 3134, "s": 5}, {"i": 1624, "s": 6}, {"i": 6454, "s": 3}, {"i": 3933, "s": 5}, {"i": 8759, "s": 8}, {"i": 5681, "s": 4}, {"i": 725, "s": 9}, {"i": 6736, "s": 7}, {"i": 5505, "s": 4}, {"i": 2312, "s": 4}, {"i": 4870, "s": 6}, {"i": 3722, "s": 5}, {"i": 8500, "s": 13}, {"i": 5025, "s": 9}, {"i": 8347, "s": 6}, {"i": 4551, "s": 4}, {"i": 4552, "s": 6}, {"i": 2657, "s": 6}, {"i": 1792, "s": 6}, {"i": 8282, "s": 8}, {"i": 1746, "s": 15}, {"i": 4871, "s": 7}, {"i": 1794, "s": 10}, {"i": 5871, "s": 7}, {"i": 5508, "s": 11}, {"i": 9862, "s": 15}, {"i": 5557, "s": 8}, {"i": 6460, "s": 5}, {"i": 9228, "s": 9}, {"i": 4645, "s": 3}, {"i": 5991, "s": 6}, {"i": 8456, "s": 3}, {"i": 1011, "s": 6}, {"i": 7210, "s": 4}, {"i": 6525, "s": 10}, {"i": 4151, "s": 4}, {"i": 3339, "s": 3}, {"i": 92, "s": 6}, {"i": 5702, "s": 7}, {"i": 8182, "s": 4}, {"i": 466, "s": 20}, {"i": 4032, "s": 10}, {"i": 7846, "s": 6}, {"i": 6571, "s": 6}, {"i": 1092, "s": 5}, {"i": 4998, "s": 3}, {"i": 3283, "s": 5}, {"i": 5095, "s": 23}, {"i": 4772, "s": 5}, {"i": 233, "s": 8}, {"i": 5940, "s": 6}, {"i": 9833, "s": 3}, {"i": 4228, "s": 9}, {"i": 2671, "s": 3}, {"i": 2822, "s": 3}, {"i": 5, "s": 3}, {"i": 5908, "s": 5}, {"i": 9935, "s": 6}, {"i": 7952, "s": 11}, {"i": 8963, "s": 3}, {"i": 5696, "s": 9}, {"i": 3785, "s": 7}, {"i": 9758, "s": 5}, {"i": 664, "s": 8}, {"i": 9028, "s": 4}, {"i": 10554, "s": 7}, {"i": 3756, "s": 4}, {"i": 4708, "s": 13}, {"i": 547, "s": 9}, {"i": 4791, "s": 3}, {"i": 1212, "s": 18}, {"i": 854, "s": 6}, {"i": 8611, "s": 8}, {"i": 6669, "s": 8}, {"i": 399, "s": 11}, {"i": 8592, "s": 8}, {"i": 10602, "s": 9}, {"i": 3743, "s": 3}, {"i": 7489, "s": 21}, {"i": 6482, "s": 3}, {"i": 4386, "s": 3}]