[{"i": 8197, "p": [160, 328]}, {"i": 8375, "p": [503, 300]}, {"i": 5778, "p": [1522, 530]}, {"i": 5410, "p": [1919, 695]}, {"i": 8462, "p": [1790, 285]}, {"i": 8173, "p": [194, 346]}, {"i": 2956, "p": [846, 942]}, {"i": 3355, "p": [658, 917]}, {"i": 1437, "p": [242, 1102]}, {"i": 5990, "p": [421, 582]}, {"i": 8646, "p": [612, 279]}, {"i": 10030, "p": [235, 96]}, {"i": 9520, "p": [954, 161]}, {"i": 3459, "p": [1838, 893]}, {"i": 8878, "p": [1111, 231]}, {"i": 7722, "p": [1648, 404]}, {"i": 9839, "p": [1513, 124]}, {"i": 8985, "p": [791, 198]}, {"i": 3860, "p": [1905, 837]}, {"i": 2414, "p": [784, 1002]}, {"i": 6818, "p": [180, 542]}, {"i": 553, "p": [1212, 1226]}, {"i": 5091, "p": [1133, 729]}, {"i": 1621, "p": [604, 1091]}, {"i": 964, "p": [2297, 1160]}, {"i": 9950, "p": [483, 91]}, {"i": 7877, "p": [2028, 351]}, {"i": 3662, "p": [865, 885]}, {"i": 5222, "p": [1354, 666]}, {"i": 2215, "p": [1092, 1032]}, {"i": 7829, "p": [1652, 392]}, {"i": 3583, "p": [635, 891]}, {"i": 789, "p": [2292, 1186]}, {"i": 6899, "p": [1898, 527]}, {"i": 3741, "p": [321, 876]}, {"i": 2992, "p": [1792, 941]}, {"i": 9238, "p": [1281, 200]}, {"i": 4652, "p": [445, 716]}, {"i": 5877, "p": [1540, 496]}, {"i": 3634, "p": [919, 858]}, {"i": 9702, "p": [563, 146]}, {"i": 252, "p": [1429, 1257]}, {"i": 3696, "p": [1013, 880]}, {"i": 7412, "p": [1912, 468]}, {"i": 9628, "p": [662, 150]}, {"i": 6111, "p": [1464, 623]}, {"i": 1780, "p": [2042, 1027]}, {"i": 9360, "p": [1341, 189]}, {"i": 4830, "p": [599, 755]}, {"i": 6101, "p": [2130, 666]}, {"i": 4973, "p": [1723, 651]}, {"i": 4199, "p": [1435, 818]}, {"i": 5783, "p": [1240, 529]}, {"i": 8938, "p": [1011, 237]}, {"i": 3927, "p": [1728, 854]}, {"i": 6696, "p": [772, 578]}, {"i": 9791, "p": [1792, 106]}, {"i": 1680, "p": [381, 1085]}, {"i": 9266, "p": [177, 186]}, {"i": 7718, "p": [827, 414]}, {"i": 8821, "p": [767, 254]}, {"i": 1383, "p": [1352, 1103]}, {"i": 4041, "p": [1366, 830]}, {"i": 2445, "p": [2109, 972]}, {"i": 7930, "p": [605, 364]}, {"i": 5949, "p": [401, 648]}, {"i": 6592, "p": [2024, 597]}, {"i": 5164, "p": [28, 716]}, {"i": 6952, "p": [708, 524]}, {"i": 4003, "p": [1218, 837]}, {"i": 6758, "p": [1237, 555]}, {"i": 3666, "p": [1509, 884]}, {"i": 9630, "p": [2034, 154]}, {"i": 8728, "p": [485, 270]}, {"i": 2936, "p": [1766, 962]}, {"i": 7857, "p": [871, 386]}, {"i": 2920, "p": [1463, 965]}, {"i": 7561, "p": [22, 436]}, {"i": 6265, "p": [81, 645]}, {"i": 7291, "p": [36, 485]}, {"i": 8024, "p": [668, 364]}, {"i": 9257, "p": [1953, 196]}, {"i": 9003, "p": [1693, 233]}, {"i": 6861, "p": [2064, 551]}, {"i": 5354, "p": [2079, 700]}, {"i": 9497, "p": [1227, 161]}, {"i": 3489, "p": [2207, 886]}, {"i": 1029, "p": [571, 1154]}, {"i": 4312, "p": [1670, 778]}, {"i": 4263, "p": [1986, 806]}, {"i": 1931, "p": [1148, 1055]}, {"i": 7261, "p": [1366, 492]}, {"i": 535, "p": [658, 1222]}, {"i": 2139, "p": [1982, 1027]}, {"i": 8969, "p": [746, 229]}, {"i": 3777, "p": [1577, 866]}, {"i": 4770, "p": [810, 752]}, {"i": 8355, "p": [1803, 317]}, {"i": 4034, "p": [1155, 807]}, {"i": 1965, "p": [1798, 1047]}]