[{"i": 4911, "p": [63, 743]}, {"i": 2264, "p": [1916, 1002]}, {"i": 5855, "p": [1438, 505]}, {"i": 2481, "p": [1827, 961]}, {"i": 653, "p": [830, 1206]}, {"i": 2767, "p": [33, 970]}, {"i": 197, "p": [544, 1279]}, {"i": 5146, "p": [2110, 700]}, {"i": 7073, "p": [1045, 475]}, {"i": 6304, "p": [1389, 629]}, {"i": 5512, "p": [1277, 679]}, {"i": 4133, "p": [1714, 820]}, {"i": 5899, "p": [1396, 481]}, {"i": 9171, "p": [127, 200]}, {"i": 6999, "p": [753, 534]}, {"i": 6013, "p": [1931, 642]}, {"i": 7159, "p": [969, 402]}, {"i": 6434, "p": [622, 605]}, {"i": 651, "p": [1673, 1207]}, {"i": 4450, "p": [1981, 754]}, {"i": 3346, "p": [2149, 898]}, {"i": 2183, "p": [1940, 953]}, {"i": 4205, "p": [1867, 821]}, {"i": 10320, "p": [2058, 64]}, {"i": 8707, "p": [1525, 235]}, {"i": 145, "p": [2211, 1293]}, {"i": 10461, "p": [329, 27]}, {"i": 8593, "p": [340, 284]}, {"i": 6812, "p": [172, 556]}, {"i": 2964, "p": [46, 956]}, {"i": 5392, "p": [1810, 623]}, {"i": 6524, "p": [956, 594]}, {"i": 5304, "p": [1048, 698]}, {"i": 10100, "p": [933, 83]}, {"i": 1302, "p": [1406, 1086]}, {"i": 3141, "p": [963, 840]}, {"i": 10041, "p": [1904, 95]}, {"i": 188, "p": [1348, 1263]}, {"i": 5582, "p": [1522, 674]}, {"i": 8718, "p": [1634, 262]}, {"i": 1432, "p": [935, 1098]}, {"i": 9694, "p": [554, 140]}, {"i": 2845, "p": [1272, 905]}, {"i": 6853, "p": [2295, 563]}, {"i": 10145, "p": [163, 77]}, {"i": 8720, "p": [1630, 250]}, {"i": 1287, "p": [1004, 1094]}, {"i": 321, "p": [2160, 1259]}, {"i": 2668, "p": [1164, 975]}, {"i": 3390, "p": [1193, 913]}, {"i": 3955, "p": [336, 846]}, {"i": 8914, "p": [260, 224]}, {"i": 5407, "p": [1493, 680]}, {"i": 8885, "p": [945, 227]}, {"i": 4392, "p": [1897, 731]}, {"i": 6573, "p": [1772, 596]}, {"i": 5498, "p": [1915, 683]}, {"i": 9273, "p": [1278, 186]}, {"i": 6919, "p": [1591, 543]}, {"i": 5868, "p": [1451, 500]}, {"i": 5957, "p": [398, 634]}, {"i": 3044, "p": [1878, 933]}, {"i": 9897, "p": [254, 118]}, {"i": 4261, "p": [268, 808]}, {"i": 502, "p": [1960, 1231]}, {"i": 9311, "p": [1604, 174]}, {"i": 6749, "p": [1005, 554]}, {"i": 511, "p": [453, 1221]}, {"i": 2358, "p": [202, 1010]}, {"i": 5889, "p": [1158, 487]}, {"i": 2539, "p": [1067, 978]}, {"i": 403, "p": [1176, 1212]}, {"i": 2198, "p": [1967, 941]}, {"i": 3689, "p": [836, 868]}, {"i": 7395, "p": [916, 476]}, {"i": 3209, "p": [518, 926]}, {"i": 3440, "p": [1443, 901]}, {"i": 7996, "p": [489, 370]}, {"i": 1596, "p": [1891, 1095]}, {"i": 5591, "p": [2132, 677]}, {"i": 1541, "p": [1631, 935]}, {"i": 3928, "p": [1715, 846]}, {"i": 745, "p": [2101, 1178]}, {"i": 5266, "p": [1107, 706]}, {"i": 9883, "p": [432, 37]}, {"i": 2992, "p": [1792, 941]}, {"i": 5771, "p": [1203, 532]}, {"i": 2035, "p": [1999, 1030]}, {"i": 1081, "p": [2249, 1127]}, {"i": 1458, "p": [1473, 1101]}, {"i": 3017, "p": [1437, 931]}, {"i": 1721, "p": [312, 1086]}, {"i": 2520, "p": [525, 994]}, {"i": 1042, "p": [695, 1141]}, {"i": 4949, "p": [1640, 684]}, {"i": 3161, "p": [1038, 810]}, {"i": 1113, "p": [1522, 1143]}, {"i": 3421, "p": [781, 900]}, {"i": 8601, "p": [2277, 277]}, {"i": 9695, "p": [557, 134]}]